Metadata-Version: 1.0
Name: csv2arff
Version: 1.8
Summary: Csv to Arff converter
Home-page: https://github.com/ugursogukpinar/csv2arff
Author: Uğur Soğukpınar
Author-email: sogukpinar.ugur@gmail.com
License: LICENSE.txt
Platform: UNKNOWN
